saweriaqris.py
saweriaqris-0.2.1.dist-info/licenses/LICENSE
saweriaqris-0.2.1.dist-info/METADATA
saweriaqris-0.2.1.dist-info/WHEEL
saweriaqris-0.2.1.dist-info/top_level.txt
saweriaqris-0.2.1.dist-info/RECORD
