Metadata-Version: 2.4
Name: saweriaqris
Version: 0.2.1
Summary: Saweria QRIS code generator
Author-email: nindtz <nindita@gmail.com>
License: MIT
Project-URL: Source Code, http://github.com/nindtz/saweriaqris
Project-URL: Funding, https://ko-fi.com/nindtz
Keywords: qris,saweria,payments
Classifier: Programming Language :: Python :: 3
Classifier: License :: OSI Approved :: MIT License
Classifier: Operating System :: OS Independent
License-File: LICENSE
Requires-Dist: beautifulsoup4
Requires-Dist: httpx
Dynamic: license-file
